nvmetools/__init__.py
nvmetools/apps/fio.py
nvmetools/apps/nvmecmd.py
nvmetools/console/checknvme.py
nvmetools/console/listnvme.py
nvmetools/console/readnvme.py
nvmetools/console/testnvme.py
nvmetools/console/updatenvme.py
nvmetools/console/viewnvme.py
nvmetools/lib/nvme/__init__.py
nvmetools/lib/nvme/framework.py
nvmetools/lib/nvme/pdf_reporter.py
nvmetools/lib/nvme/reporter.py
nvmetools/lib/nvme/cases/__init__.py
nvmetools/lib/nvme/cases/cycle/power_cycle.py
nvmetools/lib/nvme/cases/cycle/reset_cycle.py
nvmetools/lib/nvme/cases/features/format.py
nvmetools/lib/nvme/cases/features/power_loss_protection.py
nvmetools/lib/nvme/cases/features/timestamp.py
nvmetools/lib/nvme/cases/firmware/firmware_activate.py
nvmetools/lib/nvme/cases/firmware/firmware_download.py
nvmetools/lib/nvme/cases/firmware/firmware_security.py
nvmetools/lib/nvme/cases/firmware/firmware_update.py
nvmetools/lib/nvme/cases/info/admin_commands.py
nvmetools/lib/nvme/cases/info/suite_end_info.py
nvmetools/lib/nvme/cases/info/suite_start_info.py
nvmetools/lib/nvme/cases/performance/address_alignment.py
nvmetools/lib/nvme/cases/performance/big_file_reads.py
nvmetools/lib/nvme/cases/performance/big_file_writes.py
nvmetools/lib/nvme/cases/performance/data_compression.py
nvmetools/lib/nvme/cases/performance/data_deduplication.py
nvmetools/lib/nvme/cases/performance/idle_latency.py
nvmetools/lib/nvme/cases/performance/long_burst_lib.py
nvmetools/lib/nvme/cases/performance/long_burst_performance.py
nvmetools/lib/nvme/cases/performance/long_burst_performance_full.py
nvmetools/lib/nvme/cases/performance/read_buffer.py
nvmetools/lib/nvme/cases/performance/short_burst_performance.py
nvmetools/lib/nvme/cases/performance/short_burst_performance_full.py
nvmetools/lib/nvme/cases/performance/trim.py
nvmetools/lib/nvme/cases/selftest/extended_selftest.py
nvmetools/lib/nvme/cases/selftest/short_diagnostic.py
nvmetools/lib/nvme/cases/selftest/short_selftest.py
nvmetools/lib/nvme/cases/smart/background_smart.py
nvmetools-0.8.0.dist-info/LICENSE
nvmetools-0.8.0.dist-info/METADATA
nvmetools-0.8.0.dist-info/WHEEL
nvmetools-0.8.0.dist-info/entry_points.txt
nvmetools-0.8.0.dist-info/top_level.txt
nvmetools-0.8.0.dist-info/RECORD
