Metadata-Version: 2.1
Name: nvmetools
Version: 0.8.0
Summary: Basic tools for working with NVMe SSD on Windows or Linux
Author-email: Joe Jones <joejones@chargetrap.com>
Project-URL: Homepage, https://www.nvmetools.com
Project-URL: Repository, https://github.com/jtjones1001/nvmetools.git
Project-URL: Documentation, https://nvmetools.readthedocs.io/en/latest/
Keywords: nvme,ssd
Classifier: License :: OSI Approved :: MIT License
Classifier: Operating System :: POSIX :: Linux
Classifier: Operating System :: Microsoft :: Windows
Classifier: Programming Language :: Python :: 3
Requires-Python: >=3.9
License-File: LICENSE
Requires-Dist: numpy
Requires-Dist: psutil
Requires-Dist: matplotlib
Requires-Dist: reportlab
Requires-Dist: cycler
Provides-Extra: dev
Requires-Dist: black ; extra == 'dev'
Requires-Dist: flake8 ; extra == 'dev'
Requires-Dist: pytest ; extra == 'dev'
